aicodeprep_gui/__init__.py
aicodeprep_gui/apptheme.py
aicodeprep_gui/config.py
aicodeprep_gui/file_processor.py
aicodeprep_gui/linux_installer.py
aicodeprep_gui/macos_installer.py
aicodeprep_gui/main.py
aicodeprep_gui/smart_logic.py
aicodeprep_gui/update_checker.py
aicodeprep_gui/windows_registry.py
aicodeprep_gui/data/AICodePrep.workflow.zip
aicodeprep_gui/data/default_config.toml
aicodeprep_gui/data/flow.json
aicodeprep_gui/data/flow_studio_help.html
aicodeprep_gui/data/fonts/FiraCode-VariableFont_wght.ttf
aicodeprep_gui/data/fonts/JetBrainsMono-VariableFont_wght.ttf
"aicodeprep_gui/data/fonts/NotoSans-VariableFont_wdth,wght.ttf"
aicodeprep_gui/data/fonts/SpaceMono-Regular.ttf
aicodeprep_gui/gui/__init__.py
aicodeprep_gui/gui/main_window.py
aicodeprep_gui/gui/components/__init__.py
aicodeprep_gui/gui/components/dialogs.py
aicodeprep_gui/gui/components/installer_dialogs.py
aicodeprep_gui/gui/components/language_dialog.py
aicodeprep_gui/gui/components/layouts.py
aicodeprep_gui/gui/components/multi_state_level_delegate.py
aicodeprep_gui/gui/components/preset_buttons.py
aicodeprep_gui/gui/components/tree_widget.py
aicodeprep_gui/gui/handlers/__init__.py
aicodeprep_gui/gui/handlers/file_events.py
aicodeprep_gui/gui/handlers/keyboard_handler.py
aicodeprep_gui/gui/handlers/ui_events.py
aicodeprep_gui/gui/handlers/update_events.py
aicodeprep_gui/gui/settings/__init__.py
aicodeprep_gui/gui/settings/preferences.py
aicodeprep_gui/gui/settings/presets.py
aicodeprep_gui/gui/settings/ui_settings.py
aicodeprep_gui/gui/utils/__init__.py
aicodeprep_gui/gui/utils/helpers.py
aicodeprep_gui/gui/utils/metrics.py
aicodeprep_gui/i18n/__init__.py
aicodeprep_gui/i18n/translator.py
aicodeprep_gui/i18n/translations/aicodeprep_gui_ar.qm
aicodeprep_gui/i18n/translations/aicodeprep_gui_da.qm
aicodeprep_gui/i18n/translations/aicodeprep_gui_de.qm
aicodeprep_gui/i18n/translations/aicodeprep_gui_en.qm
aicodeprep_gui/i18n/translations/aicodeprep_gui_es.qm
aicodeprep_gui-1.3.2.dist-info/licenses/SUSTAINABLE-LICENSE
aicodeprep_gui-1.3.2.dist-info/METADATA
aicodeprep_gui-1.3.2.dist-info/WHEEL
aicodeprep_gui-1.3.2.dist-info/entry_points.txt
aicodeprep_gui-1.3.2.dist-info/top_level.txt
aicodeprep_gui-1.3.2.dist-info/RECORD
