Metadata-Version: 2.4
Name: aicodeprep-gui
Version: 1.3.2
Summary: A smart GUI to select, filter, and concatenate code files for large language model (LLM) and AI analysis.
Author-email: Tom Brothers <tom@wuu73.org>
License-Expression: LicenseRef-SUSTAINABLE
Project-URL: Homepage, https://github.com/detroittommy879/aicodeprep-gui
Keywords: ai,code,preparation,llm,gui,pyside6
Classifier: Programming Language :: Python
Classifier: Programming Language :: Python :: 3
Classifier: Operating System :: OS Independent
Classifier: Topic :: Software Development
Classifier: Environment :: X11 Applications :: Qt
Classifier: Environment :: Win32 (MS Windows)
Classifier: Environment :: MacOS X
Requires-Python: <3.14,>=3.9
License-File: SUSTAINABLE-LICENSE
Requires-Dist: PySide6<6.10,>=6.9
Requires-Dist: toml
Requires-Dist: NodeGraphQt
Requires-Dist: pathspec
Requires-Dist: requests
Requires-Dist: packaging
Requires-Dist: Pygments>=2.18.0
Requires-Dist: litellm>=1.40.0
Requires-Dist: setuptools>=65.0.0
Provides-Extra: build
Requires-Dist: pyinstaller>=6.0.0; extra == "build"
Requires-Dist: pyinstaller-hooks-contrib; extra == "build"
Requires-Dist: setuptools; extra == "build"
Requires-Dist: wheel; extra == "build"
Dynamic: license-file
